{"is_source_file": true, "format": "JavaScript (React JSX)", "description": "A React functional component named Footer that renders a footer section with current year and branding text.", "external_files": [], "external_methods": ["React"], "published": [], "classes": [], "methods": [{"name": "Footer()", "description": "A React functional component rendering footer content with dynamic current year.", "scope": "", "scopeKind": ""}], "calls": ["React"], "search-terms": ["Footer", "React component", "footer HTML", "current year", "branding"], "state": 2, "file_id": 25, "knowledge_revision": 74, "git_revision": "dd8a3a54c7956d472d9edadf6fa4e05c65c8b74b", "ctags": [{"_type": "tag", "name": "Footer", "path": "/home/kavia/workspace/code-generation/test-automation-dashboard-2596-6096/frontend_react_app/src/components/ui/Footer.js", "pattern": "/^export default function Footer() {$/", "language": "JavaScript", "kind": "function", "signature": "()"}], "hash": "2a23ec4f2c993696820fd2b7dabcae67", "format-version": 4, "code-base-name": "frontend_react_app", "filename": "frontend_react_app/src/components/ui/Footer.js", "revision_history": [{"74": "dd8a3a54c7956d472d9edadf6fa4e05c65c8b74b"}]}